image_processing/__init__.py
image_processing/combination.py
image_processing/transformation.py
image_processing_drigonato/__init__.py
image_processing_drigonato/combination.py
image_processing_drigonato/transformation.py
image_processing_drigonato-0.0.1.dist-info/METADATA
image_processing_drigonato-0.0.1.dist-info/WHEEL
image_processing_drigonato-0.0.1.dist-info/top_level.txt
image_processing_drigonato-0.0.1.dist-info/RECORD
