Metadata-Version: 2.1
Name: image-processing-drigonato
Version: 0.0.1
Summary: Processamento de imagens usando Skimage
Home-page: https://github.com/dorigonato/image-processing-package.git
Author: Dorival
Requires-Python: >=3.8
